README.txt
setup.py
Products/__init__.py
Products.EasyUserAuthenticator.egg-info/PKG-INFO
Products.EasyUserAuthenticator.egg-info/SOURCES.txt
Products.EasyUserAuthenticator.egg-info/SOURCES.txt~
Products.EasyUserAuthenticator.egg-info/dependency_links.txt
Products.EasyUserAuthenticator.egg-info/entry_points.txt
Products.EasyUserAuthenticator.egg-info/namespace_packages.txt
Products.EasyUserAuthenticator.egg-info/not-zip-safe
Products.EasyUserAuthenticator.egg-info/requires.txt
Products.EasyUserAuthenticator.egg-info/top_level.txt
Products/EasyUserAuthenticator/Makefile
Products/EasyUserAuthenticator/README.txt
Products/EasyUserAuthenticator/__init__.py
Products/EasyUserAuthenticator/changes.txt
Products/EasyUserAuthenticator/config.py
Products/EasyUserAuthenticator/configure.zcml
Products/EasyUserAuthenticator/plugin.py
Products/EasyUserAuthenticator/readme.txt
Products/EasyUserAuthenticator/tests.py
Products/EasyUserAuthenticator/version.txt
Products/EasyUserAuthenticator/zope2.py
Products/EasyUserAuthenticator/www/addEasyUserAuthentication.zpt