Metadata-Version: 1.0
Name: Products.EasyUserAuthenticator
Version: 1.0.1
Summary: Basic IMAP authentication plugin, suitable for customization towards other authentication backends
Home-page: http://www.nidelven-it.no/d
Author: Morten W. Petersen
Author-email: info@nidelven-it.no
License: GPL
Keywords: python zope pas authentication imap silva plone
Platform: UNKNOWN
Classifier: Programming Language :: Python
Classifier: Framework :: Zope2
Classifier: Intended Audience :: Developers
Classifier: Intended Audience :: System Administrators
Classifier: Operating System :: OS Independent
Classifier: Topic :: Communications :: Email
Classifier: Topic :: System :: Systems Administration :: Authentication/Directory
